mugwort/__init__.py
mugwort/basic/__init__.py
mugwort/basic/logger.py
mugwort/basic/multitask.py
mugwort/tools/__init__.py
mugwort/tools/cryptor/__init__.py
mugwort/tools/cryptor/aes_cryptor.py
mugwort/tools/cryptor/des_cryptor.py
mugwort/tools/cryptor/ed25519_cryptor.py
mugwort/tools/cryptor/rsa_cryptor.py
mugwort/tools/cryptor/totp_cryptor.py
mugwort/tools/cryptor/x25519_cryptor.py
mugwort/tools/cryptor/x509_cryptor.py
mugwort/tools/database/__init__.py
mugwort/tools/database/elasticsearch_helper.py
mugwort/tools/database/hbase_helper.py
mugwort/tools/database/memcached_helper.py
mugwort/tools/database/mongodb_helper.py
mugwort/tools/database/mysql_helper.py
mugwort/tools/database/oracle_helper.py
mugwort/tools/database/postgresql_helper.py
mugwort/tools/database/redis_helper.py
mugwort/tools/database/sqlite3_helper.py
mugwort/tools/database/sqlserver_helper.py
mugwort/tools/proxy/__init__.py
mugwort/tools/proxy/clash_proxy.py
mugwort-0.5.5.dist-info/LICENSE
mugwort-0.5.5.dist-info/WHEEL
mugwort-0.5.5.dist-info/METADATA
mugwort-0.5.5.dist-info/RECORD
