Metadata-Version: 2.1
Name: mugwort
Version: 0.5.5
Summary: 一套由各种小脚本堆砌而成的工具集，主要用于爬虫和数据治理。
Author-email: YongJie-Xie <fsswxyj@qq.com>
Requires-Python: >=3.6.2,<4
Classifier: Development Status :: 3 - Alpha
Classifier: Intended Audience :: Developers
Classifier: Intended Audience :: Information Technology
Classifier: License :: OSI Approved :: MIT License
Classifier: Natural Language :: Chinese (Simplified)
Classifier: Operating System :: Microsoft :: Windows
Classifier: Programming Language :: Python
Classifier: Programming Language :: Python :: 3 :: Only
Classifier: Programming Language :: Python :: 3.6
Classifier: Programming Language :: Python :: 3.7
Classifier: Programming Language :: Python :: 3.8
Classifier: Programming Language :: Python :: 3.9
Classifier: Programming Language :: Python :: 3.10
Classifier: Programming Language :: Python :: 3.11
Classifier: Topic :: Software Development
Classifier: Topic :: Software Development :: Libraries
Classifier: Topic :: Software Development :: Libraries :: Python Modules
Requires-Dist: colorama
Requires-Dist: apscheduler ; extra == "all"
Requires-Dist: cryptography ; extra == "all"
Requires-Dist: cx_Oracle ; extra == "all"
Requires-Dist: DBUtils ; extra == "all"
Requires-Dist: elasticsearch ; extra == "all"
Requires-Dist: mysqlclient ; extra == "all"
Requires-Dist: phoenixdb ; extra == "all"
Requires-Dist: psycopg2 ; extra == "all"
Requires-Dist: pymongo ; extra == "all"
Requires-Dist: pymssql ; extra == "all"
Requires-Dist: python-memcached ; extra == "all"
Requires-Dist: pyyaml ; extra == "all"
Requires-Dist: redis ; extra == "all"
Requires-Dist: requests ; extra == "all"
Requires-Dist: cryptography ; extra == "cryptor"
Requires-Dist: elasticsearch ; extra == "database-elasticsearch"
Requires-Dist: DBUtils ; extra == "database-hbase"
Requires-Dist: phoenixdb ; extra == "database-hbase"
Requires-Dist: python-memcached ; extra == "database-memcached"
Requires-Dist: DBUtils ; extra == "database-mongodb"
Requires-Dist: pymongo ; extra == "database-mongodb"
Requires-Dist: DBUtils ; extra == "database-mysql"
Requires-Dist: mysqlclient ; extra == "database-mysql"
Requires-Dist: DBUtils ; extra == "database-oracle"
Requires-Dist: cx_Oracle ; extra == "database-oracle"
Requires-Dist: DBUtils ; extra == "database-postgresql"
Requires-Dist: psycopg2 ; extra == "database-postgresql"
Requires-Dist: redis ; extra == "database-redis"
Requires-Dist: DBUtils ; extra == "database-sqlserver"
Requires-Dist: pymssql ; extra == "database-sqlserver"
Requires-Dist: requests ; extra == "proxy-clash"
Requires-Dist: pyyaml ; extra == "proxy-clash"
Requires-Dist: apscheduler ; extra == "proxy-clash"
Requires-Dist: pytest ; extra == "test"
Requires-Dist: pytest-cov ; extra == "test"
Project-URL: Source, https://github.com/YongJie-Xie/MugwortTools
Project-URL: Tracker, https://github.com/YongJie-Xie/MugwortTools/issues
Provides-Extra: all
Provides-Extra: cryptor
Provides-Extra: database-elasticsearch
Provides-Extra: database-hbase
Provides-Extra: database-memcached
Provides-Extra: database-mongodb
Provides-Extra: database-mysql
Provides-Extra: database-oracle
Provides-Extra: database-postgresql
Provides-Extra: database-redis
Provides-Extra: database-sqlserver
Provides-Extra: proxy-clash
Provides-Extra: test
